StreamDeck_Client/StreamDeck-Client.py
StreamDeck_Client/__init__.py
StreamDeck_Client/backend/__init__.py
StreamDeck_Client/backend/client.py
StreamDeck_Client/ui/Buttons.py
StreamDeck_Client/ui/NavBar.py
StreamDeck_Client/ui/Window.py
StreamDeck_Client/ui/__init__.py
StreamDeck_Client-0.0.3a0.dist-info/METADATA
StreamDeck_Client-0.0.3a0.dist-info/WHEEL
StreamDeck_Client-0.0.3a0.dist-info/top_level.txt
StreamDeck_Client-0.0.3a0.dist-info/RECORD
