Metadata-Version: 2.1
Name: StreamDeck-Client
Version: 0.0.3a0
Summary: Use any device which can run python as a streamdeck like a Raspberry Pi
Home-page: https://github.com/philliphqs/StreamDeck
Author: philliphqs
Author-email: contact@hqsartworks.me
License: MIT
Platform: UNKNOWN
Classifier: License :: OSI Approved :: MIT License
Classifier: Programming Language :: Python :: 3
Classifier: Programming Language :: Python :: 3.9
Requires-Dist: requests
Requires-Dist: dearpygui
